django_serverless_emailer/__init__.py
django_serverless_emailer/apps.py
django_serverless_emailer/core.py
django_serverless_emailer/sources.py
django_serverless_emailer/templates/django_serverless_emailer/step-function.html
django_serverless_emailer-0.3.0.dist-info/WHEEL
django_serverless_emailer-0.3.0.dist-info/METADATA
django_serverless_emailer-0.3.0.dist-info/RECORD
