Metadata-Version: 2.1
Name: django-serverless-emailer
Version: 0.3.0
Summary: Provides a lambda handler for sending emails concerning errors in AWS
Home-page: https://github.com/Kicksaw-Consulting/django-serverless-emailer
License: MIT
Keywords: django,aws,serverless,email
Author: Alex Drozd
Author-email: drozdster@gmail.com
Requires-Python: >=3.8,<4.0
Classifier: License :: OSI Approved :: MIT License
Classifier: Programming Language :: Python :: 3
Classifier: Programming Language :: Python :: 3.8
Classifier: Programming Language :: Python :: 3.9
Requires-Dist: Django (>=3.2,<4.0)
Project-URL: Repository, https://github.com/Kicksaw-Consulting/django-serverless-emailer
